{ "items": [
  { "title": "Glavna_stranica", "rev": "5109344" },
  { "title": "Tijelovo", "rev": "5146359" },
  { "title": "Dodatak:Popis_pozivnih_brojeva_država", "rev": "5105575" },
  { "title": "Hrvatska", "rev": "5137372" },
  { "title": "Katar", "rev": "5132536" },
  { "title": "Dan_državnosti_(Hrvatska)", "rev": "5148298" },
  { "title": "Victor_Hugo", "rev": "4918107" },
  { "title": "Zagreb", "rev": "5159614" },
  { "title": "Očev_dan", "rev": "5059857" },
  { "title": "Suncostaj", "rev": "5115962" },
  { "title": "Cristiano_Ronaldo", "rev": "5131956" },
  { "title": "Antun_Padovanski", "rev": "5086106" },
  { "title": "Post_u_islamu", "rev": "5155342" },
  { "title": "Dan_antifašističke_borbe", "rev": "5116129" },
  { "title": "UEFA_Liga_prvaka", "rev": "5154020" },
  { "title": "Europsko_prvenstvo_u_rukometu_-_Hrvatska_2018.", "rev": "5146372" },
  { "title": "Jure_Francetić", "rev": "4926135" },
  { "title": "Dražen_Petrović", "rev": "5092817" },
  { "title": "Island", "rev": "5106124" },
  { "title": "Severina_Vučković", "rev": "5146355" },
  { "title": "Luka_Modrić", "rev": "5144352" },
  { "title": "Dodatak:Popis_pozivnih_brojeva_u_Hrvatskoj", "rev": "5105737" },
  { "title": "Milan_Bandić", "rev": "5142000" },
  { "title": "Sveti_Petar", "rev": "5106645" },
  { "title": "Domovinski_rat", "rev": "5146673" },
  { "title": "Poskok", "rev": "5119903" },
  { "title": "Njemačka", "rev": "5156497" },
  { "title": "Portal:Životopis", "rev": "5113946" },
  { "title": "Split", "rev": "5157377" },
  { "title": "Drugi_svjetski_rat", "rev": "5112061" },
  { "title": "Prvi_svjetski_rat", "rev": "5148074" },
  { "title": "Josip_Broz_Tito", "rev": "5129779" },
  { "title": "Europa", "rev": "5144630" },
  { "title": "Duhovi_(blagdan)", "rev": "4903516" },
  { "title": "Botulizam", "rev": "4539202" },
  { "title": "Dodatak:Popis_zagrebačkih_gradonačelnika", "rev": "5130180" },
  { "title": "Ivan_Krstitelj", "rev": "5123033" },
  { "title": "Europska_unija", "rev": "5154825" },
  { "title": "Nikola_Tesla", "rev": "5115966" },
  { "title": "FIFA_Konfederacijski_kup", "rev": "5099287" },
  { "title": "Pirati_s_Kariba", "rev": "5050918" },
  { "title": "Lionel_Messi", "rev": "5156158" },
  { "title": "Bosna_i_Hercegovina", "rev": "5155871" },
  { "title": "Konzervacija_metala", "rev": "5146350" },
  { "title": "Dodatak:Popis_država", "rev": "5142142" },
  { "title": "Bruna_Esih", "rev": "5124917" },
  { "title": "Napad_na_Pearl_Harbor", "rev": "5023675" },
  { "title": "@", "rev": "5121826" },
  { "title": "Srbija", "rev": "5158228" },
  { "title": "Facebook", "rev": "5146298" },
  { "title": "Autizam", "rev": "5139569" },
  { "title": "Anksioznost", "rev": "5130684" },
  { "title": "Rafael_Nadal", "rev": "5159731" },
  { "title": "Antun_Gustav_Matoš", "rev": "5096573" },
  { "title": "Rodbinski_nazivi", "rev": "5139560" },
  { "title": "Goran_Lisica", "rev": "4915703" },
  { "title": "Sunčanica", "rev": "5082028" },
  { "title": "Rijeka", "rev": "5159832" },
  { "title": "Crna_Gora", "rev": "5110387" },
  { "title": "Zadar", "rev": "5157339" },
  { "title": "MKB-10", "rev": "3943407" },
  { "title": "Ljeto", "rev": "5133731" },
  { "title": "Rusija", "rev": "5076585" },
  { "title": "Real_Madrid_C.F.", "rev": "5090271" },
  { "title": "Ramazan", "rev": "5101343" },
  { "title": "Mario_Mandžukić", "rev": "5146354" },
  { "title": "Anka_Mrak_Taritaš", "rev": "5107661" },
  { "title": "Albert_Einstein", "rev": "5151600" },
  { "title": "Posljednji_Stipančići", "rev": "5123192" },
  { "title": "Dubrovnik", "rev": "5159598" },
  { "title": "Davor_Božinović", "rev": "5020546" },
  { "title": "Hrvatska_abeceda", "rev": "5159811" },
  { "title": "Sjedinjene_Američke_Države", "rev": "5159608" },
  { "title": "Miroslav_Krleža", "rev": "5133821" },
  { "title": "Zdravko_Mamić", "rev": "5106654" },
  { "title": "Blagdani_i_spomendani_u_Hrvatskoj", "rev": "5125216" },
  { "title": "Trokut", "rev": "5082390" },
  { "title": "Joško_Jeličić", "rev": "5085677" },
  { "title": "Nezavisna_Država_Hrvatska", "rev": "5147148" },
  { "title": "Juventus_F.C.", "rev": "5147474" },
  { "title": "Osijek", "rev": "5148194" },
  { "title": "Bol_u_donjem_dijelu_leđa", "rev": "4691054" },
  { "title": "Hrvatski_nacionalni_parkovi_i_parkovi_prirode", "rev": "5138012" },
  { "title": "Mate_Rimac", "rev": "5153307" },
  { "title": "Socijalistička_Federativna_Republika_Jugoslavija", "rev": "5134361" },
  { "title": "Internet", "rev": "5149781" },
  { "title": "Beograd", "rev": "5150184" },
  { "title": "Josephine_Baker", "rev": "3926090" },
  { "title": "Hrvatska_narodna_stranka_-_liberalni_demokrati", "rev": "5152782" },
  { "title": "Mustafa_Nadarević", "rev": "5154789" },
  { "title": "Renesansa", "rev": "5148700" },
  { "title": "Multipla_skleroza", "rev": "5079716" },
  { "title": "Hrvatske_županije", "rev": "5141411" },
  { "title": "Marko_Perković", "rev": "5113477" },
  { "title": "Bašćanska_ploča", "rev": "5159234" },
  { "title": "Orgazam", "rev": "5143828" },
  { "title": "Lijepa_naša_domovino", "rev": "5146367" },
  { "title": "Kiklop_(roman)", "rev": "5028064" },
  { "title": "Lipanj", "rev": "4210722" },
  { "title": "Australija", "rev": "5129506" },
  { "title": "Pravokutnik", "rev": "5083187" },
  { "title": "Slovenija", "rev": "5136354" },
  { "title": "Roger_Federer", "rev": "5159752" },
  { "title": "Zločin_i_kazna", "rev": "5089554" },
  { "title": "Ante_Pavelić", "rev": "5142912" },
  { "title": "Adolf_Hitler", "rev": "5068704" },
  { "title": "Mostar", "rev": "5158599" },
  { "title": "Pablo_Escobar", "rev": "5115957" },
  { "title": "Jadransko_more", "rev": "5151142" },
  { "title": "Kosovo", "rev": "5150143" },
  { "title": "Ćirilica", "rev": "5102340" },
  { "title": "Hrvatski_jezik", "rev": "5061419" },
  { "title": "Stršljeni", "rev": "5150619" },
  { "title": "Dobriša_Cesarić", "rev": "5155339" },
  { "title": "Ujedinjeno_Kraljevstvo", "rev": "5136332" },
  { "title": "Nacionalni_park_Plitvička_jezera", "rev": "5154146" },
  { "title": "Italija", "rev": "5159417" },
  { "title": "Stilske_figure", "rev": "5158812" },
  { "title": "Mateo_Kovačić", "rev": "5139867" },
  { "title": "Turska", "rev": "5130695" },
  { "title": "HNK_Hajduk_Split", "rev": "5153610" },
  { "title": "Gradovi_u_Hrvatskoj", "rev": "5029600" },
  { "title": "Novak_Đoković", "rev": "5134696" },
  { "title": "Zlatni_dvori_(televizijska_serija)", "rev": "5042511" },
  { "title": "Shizofrenija", "rev": "5124960" },
  { "title": "Stilska_sredstva", "rev": "5048252" },
  { "title": "Grb_Republike_Hrvatske", "rev": "5141465" },
  { "title": "Mononukleoza", "rev": "4529086" },
  { "title": "Zlatko_Hasanbegović", "rev": "5082557" },
  { "title": "Romantizam", "rev": "5097161" },
  { "title": "Hrvatska_nogometna_reprezentacija", "rev": "5154222" },
  { "title": "Kubični_metar", "rev": "5082862" },
  { "title": "Namaz_(islam)", "rev": "4861615" },
  { "title": "Forrest_Gump_(1994.)", "rev": "5091831" },
  { "title": "Heath_Ledger", "rev": "5067496" },
  { "title": "Savudrijska_vala", "rev": "5057562" },
  { "title": "Josip_Jelačić", "rev": "5049585" },
  { "title": "Fašizam", "rev": "5008787" },
  { "title": "Ustaše", "rev": "5096103" },
  { "title": "Gospoda_Glembajevi", "rev": "5115581" },
  { "title": "Davor_Ivo_Stier", "rev": "5039141" },
  { "title": "NATO", "rev": "5109541" },
  { "title": "Hamlet", "rev": "5155327" },
  { "title": "Makedonija", "rev": "5153058" },
  { "title": "Saudijska_Arabija", "rev": "5158390" },
  { "title": "Riđovka", "rev": "5119904" },
  { "title": "Stanislas_Wawrinka", "rev": "5119787" },
  { "title": "Šibenik", "rev": "5140003" },
  { "title": "Pozivni_broj", "rev": "5151943" },
  { "title": "Ramazanski_bajram", "rev": "5097504" },
  { "title": "Franjo_Tuđman", "rev": "5123621" },
  { "title": "Malta", "rev": "4998319" },
  { "title": "Afrika", "rev": "5114208" },
  { "title": "Arbitraža", "rev": "5105579" },
  { "title": "Francuska", "rev": "5154001" },
  { "title": "Činovi_u_Oružanim_snagama_Republike_Hrvatske", "rev": "4857840" },
  { "title": "Popis_otoka_Hrvatske", "rev": "4943043" },
  { "title": "Gianluigi_Buffon", "rev": "5142420" },
  { "title": "Sedam_svjetskih_čuda", "rev": "4882671" },
  { "title": "Ne_daj_se,_Nina", "rev": "5123571" },
  { "title": "Tupac_Shakur", "rev": "5158407" },
  { "title": "London", "rev": "5085504" },
  { "title": "Islam", "rev": "4815112" },
  { "title": "Krvne_grupe", "rev": "4944724" },
  { "title": "Slatke_male_lažljivice_(televizijska_serija)", "rev": "5124023" },
  { "title": "Realizam_(književnost)", "rev": "5024459" },
  { "title": "Hrvatska_književnost", "rev": "5090344" },
  { "title": "Sarajevo", "rev": "5154777" },
  { "title": "Kolinda_Grabar-Kitarović", "rev": "5116335" },
  { "title": "Sarkazam", "rev": "5151355" },
  { "title": "Dinosauri", "rev": "5154781" },
  { "title": "Meningitis", "rev": "5038454" },
  { "title": "Lud,_zbunjen,_normalan", "rev": "5159253" },
  { "title": "Kina", "rev": "5065176" },
  { "title": "Gramatika_latinskog_jezika", "rev": "5159098" },
  { "title": "Islamski_blagdani", "rev": "5144069" },
  { "title": "Operacija_Oluja", "rev": "5137715" },
  { "title": "Lirika", "rev": "5157941" },
  { "title": "Padež", "rev": "5134891" },
  { "title": "Cheick_Tioté", "rev": "5062257" },
  { "title": "Košarka", "rev": "5147151" },
  { "title": "Barok", "rev": "5095196" },
  { "title": "FC_Barcelona", "rev": "5155318" },
  { "title": "Fahriye_Evcen", "rev": "4967816" },
  { "title": "Svjetsko_prvenstvo_u_nogometu_-_Rusija_2018.", "rev": "5146358" },
  { "title": "Bitka_za_Vukovar", "rev": "5115959" },
  { "title": "München", "rev": "5148384" },
  { "title": "Deset_Božjih_zapovijedi", "rev": "5058436" },
  { "title": "Iran", "rev": "5072051" },
  { "title": "Aorist", "rev": "4951968" },
  { "title": "Paralelogram", "rev": "5087364" },
  { "title": "Josip_Pupačić", "rev": "5028716" },
  { "title": "Švicarska", "rev": "5107250" },
  { "title": "Jehovini_svjedoci", "rev": "5156804" },
  { "title": "Uholaže", "rev": "5093866" },
  { "title": "Austrija", "rev": "5140353" },
  { "title": "Ujedinjeni_Arapski_Emirati", "rev": "4888554" },
  { "title": "William_Shakespeare", "rev": "5120456" },
  { "title": "Književni_rodovi", "rev": "5072800" },
  { "title": "Glagoljica", "rev": "5022259" },
  { "title": "Pula", "rev": "5127599" },
  { "title": "Albanija", "rev": "5141025" },
  { "title": "Sedam_smrtnih_grijeha", "rev": "5138309" },
  { "title": "Dodatak:Popis_pozivnih_brojeva_u_Bosni_i_Hercegovini", "rev": "5086057" },
  { "title": "Boja", "rev": "5119219" },
  { "title": "Aleksandar_Vučić", "rev": "5146371" },
  { "title": "Oksimoron", "rev": "5132588" },
  { "title": "Rafael_Boban", "rev": "5130727" },
  { "title": "Izrael", "rev": "5120991" },
  { "title": "Kvadratna_jednadžba", "rev": "5069618" },
  { "title": "Željko_Kerum", "rev": "4102760" },
  { "title": "Sinestezija", "rev": "5006605" },
  { "title": "Poljska", "rev": "5144507" },
  { "title": "Modernizam_(književnost)", "rev": "4542515" },
  { "title": "Lidija_Bačić", "rev": "5152292" },
  { "title": "Krpelji", "rev": "5093432" },
  { "title": "Milutin_Cihlar_Nehajev", "rev": "4764554" },
  { "title": "Prijedlozi", "rev": "5158396" },
  { "title": "Đorđe_Balašević", "rev": "5098206" },
  { "title": "Gustoća", "rev": "5001387" },
  { "title": "Savka_Dabčević-Kučar", "rev": "5061727" },
  { "title": "Zekat", "rev": "5095904" },
  { "title": "Domaća_mačka", "rev": "5154689" },
  { "title": "Registarske_oznake_za_vozila_u_Republici_Hrvatskoj", "rev": "5026034" },
  { "title": "Osmansko_Carstvo", "rev": "5120800" },
  { "title": "Rima", "rev": "4987791" },
  { "title": "LeBron_James", "rev": "5159238" },
  { "title": "Dan_D", "rev": "5066857" },
  { "title": "Karlovac", "rev": "5150258" },
  { "title": "Kanada", "rev": "5092739" },
  { "title": "Obični_jelenak", "rev": "4992366" },
  { "title": "Wikicitat", "rev": "5022497" },
  { "title": "Trapez_(geometrija)", "rev": "5133293" },
  { "title": "Horoskop", "rev": "4924812" },
  { "title": "Književnost", "rev": "5092399" },
  { "title": "Finale_UEFA_Lige_prvaka", "rev": "4910385" },
  { "title": "Zemlja", "rev": "5133419" },
  { "title": "Hrvatske_obrambene_snage", "rev": "5130150" },
  { "title": "Epika", "rev": "5093911" },
  { "title": "Sveti_Vid", "rev": "5146060" },
  { "title": "Hrvatska_povijest", "rev": "5156248" },
  { "title": "Pariz", "rev": "5076049" },
  { "title": "Kravosas", "rev": "4937793" },
  { "title": "Beč", "rev": "5094380" },
  { "title": "Moždani_udar", "rev": "5121326" },
  { "title": "Rat_u_Bosni_i_Hercegovini", "rev": "5096208" },
  { "title": "Glagoli", "rev": "4883938" },
  { "title": "Nogomet", "rev": "5107238" },
  { "title": "Berlin", "rev": "5095504" },
  { "title": "Novi_Zeland", "rev": "5114685" },
  { "title": "Gušterača", "rev": "4503539" },
  { "title": "Krk", "rev": "5107233" },
  { "title": "Zlatan_Ibrahimović", "rev": "5125941" },
  { "title": "Belot", "rev": "5137285" },
  { "title": "Irska", "rev": "5159321" },
  { "title": "GNK_Dinamo_Zagreb", "rev": "5114054" },
  { "title": "Sonet", "rev": "5150825" },
  { "title": "Biblija", "rev": "4925992" },
  { "title": "Grčka_mitologija", "rev": "5131872" },
  { "title": "Bjelančevine", "rev": "5099003" },
  { "title": "Španjolska", "rev": "5155880" },
  { "title": "Etika", "rev": "5141555" },
  { "title": "New_York_City,_New_York", "rev": "5134948" },
  { "title": "Norveška", "rev": "5146045" },
  { "title": "Wikipedija:Kafić", "rev": "5159974" },
  { "title": "Kvadrat", "rev": "5091700" },
  { "title": "Varaždin", "rev": "5148188" },
  { "title": "Godišnja_doba", "rev": "5157050" },
  { "title": "Odbojka", "rev": "5095356" },
  { "title": "Djetelina", "rev": "5154055" },
  { "title": "Elizabeta_II.", "rev": "5146360" },
  { "title": "Janica_Kostelić", "rev": "5076808" },
  { "title": "Marin_Čilić", "rev": "5111341" },
  { "title": "Majčina_dušica", "rev": "5125232" },
  { "title": "Dunav", "rev": "5147212" },
  { "title": "Ptice", "rev": "5114321" },
  { "title": "Ivan_Vrdoljak", "rev": "4987580" },
  { "title": "Harry_Potter", "rev": "5134889" },
  { "title": "Kurban-bajram", "rev": "4640967" },
  { "title": "Oprah_Winfrey", "rev": "4773156" },
  { "title": "Jednadžba_pravca", "rev": "4876083" },
  { "title": "Palatalizacija", "rev": "5071602" },
  { "title": "Indija", "rev": "4932376" },
  { "title": "Petra_Martić", "rev": "5134666" },
  { "title": "Jelena_Rozga", "rev": "5144556" },
  { "title": "Justin_Bieber", "rev": "5020145" },
  { "title": "Kugla", "rev": "5055186" },
  { "title": "Dubai", "rev": "5156837" },
  { "title": "Sedam_darova_Duha_Svetoga", "rev": "5070695" },
  { "title": "Kortikosteroidi", "rev": "4733565" },
  { "title": "Hrvatski_sabor", "rev": "5107106" },
  { "title": "MDMA", "rev": "5146474" },
  { "title": "Donald_Trump", "rev": "5115958" },
  { "title": "Pobačaj", "rev": "5082863" },
  { "title": "Lovac_u_žitu", "rev": "4935570" },
  { "title": "Istanbul", "rev": "5107335" },
  { "title": "Aspergerov_sindrom", "rev": "5114801" },
  { "title": "Bruce_Lee", "rev": "4914940" },
  { "title": "Brazil", "rev": "5083866" },
  { "title": "Švedska", "rev": "5061422" },
  { "title": "Aminokiselina", "rev": "5082068" },
  { "title": "Operacija_Lipanjske_zore", "rev": "4546778" },
  { "title": "Hedonizam", "rev": "4860225" },
  { "title": "Sociopat", "rev": "5146192" },
  { "title": "Ranko_Marinković", "rev": "5045767" },
  { "title": "Hrvati", "rev": "5147406" },
  { "title": "Istra", "rev": "5107232" },
  { "title": "Grčka", "rev": "5107270" },
  { "title": "Imperfekt", "rev": "5046514" },
  { "title": "DJ_Krmak", "rev": "5134343" },
  { "title": "Conor_McGregor", "rev": "5152407" },
  { "title": "Krv", "rev": "5153727" },
  { "title": "Nizozemska", "rev": "5128356" },
  { "title": "Hrvatska_rukometna_reprezentacija", "rev": "5153650" },
  { "title": "Iluminati", "rev": "5158914" },
  { "title": "Fotosinteza", "rev": "5153434" },
  { "title": "Austro-Ugarska", "rev": "5153205" },
  { "title": "Rečenica", "rev": "5155904" },
  { "title": "Marin_Držić", "rev": "5099516" },
  { "title": "Svetlana_Ražnatović", "rev": "5135352" },
  { "title": "Fjodor_Mihajlovič_Dostojevski", "rev": "5078044" },
  { "title": "Zinédine_Zidane", "rev": "5150608" },
  { "title": "Slavko_Mihalić", "rev": "4953661" },
  { "title": "Rukomet", "rev": "5157494" },
  { "title": "Ravnodnevica", "rev": "5151452" },
  { "title": "Vidovdan", "rev": "4570344" },
  { "title": "Maslačak", "rev": "5139400" },
  { "title": "Elektromagnetska_indukcija", "rev": "5127605" },
  { "title": "Volkswagen_Golf", "rev": "5041171" },
  { "title": "Ivo_Andrić", "rev": "5015739" },
  { "title": "Belgija", "rev": "5101456" },
  { "title": "Shakira", "rev": "5139439" },
  { "title": "Električna_energija", "rev": "5107312" },
  { "title": "Komunizam", "rev": "5125819" },
  { "title": "Ljudska_probava", "rev": "4987590" },
  { "title": "BMW_serije_3", "rev": "5120373" },
  { "title": "Parkinsonova_bolest", "rev": "5057607" },
  { "title": "BDSM", "rev": "5062135" },
  { "title": "Dubrovačka_Republika", "rev": "5138243" },
  { "title": "Snaga", "rev": "4875277" },
  { "title": "Slavonski_Brod", "rev": "5149045" },
  { "title": "Jednakostranični_trokut", "rev": "5074096" },
  { "title": "Neum", "rev": "5155572" },
  { "title": "Černobilska_katastrofa", "rev": "5093617" },
  { "title": "Zastava_Republike_Hrvatske", "rev": "5154821" },
  { "title": "Rim", "rev": "5114313" },
  { "title": "Crna_legija", "rev": "5071091" },
  { "title": "Kokain", "rev": "5062632" },
  { "title": "Popis_trigonometrijskih_identiteta", "rev": "4998427" },
  { "title": "Paradoks", "rev": "5061568" },
  { "title": "Zmije", "rev": "5097460" },
  { "title": "Drama", "rev": "5074771" },
  { "title": "Antigona", "rev": "5020813" },
  { "title": "Realni_broj", "rev": "5127199" },
  { "title": "Pomoć:Sadržaj", "rev": "4736268" },
  { "title": "Kontinent", "rev": "5068521" },
  { "title": "Mađarska", "rev": "5125951" },
  { "title": "Blavor", "rev": "5010855" },
  { "title": "Massimo_Savić", "rev": "5091098" },
  { "title": "Ježevi", "rev": "5080740" },
  { "title": "Portoriko", "rev": "5155661" },
  { "title": "Pitagorin_poučak", "rev": "5094027" },
  { "title": "Ironija", "rev": "5025939" },
  { "title": "Jetra", "rev": "5150827" },
  { "title": "Prilozi", "rev": "4988835" },
  { "title": "Voda", "rev": "5138119" },
  { "title": "Etimologija", "rev": "5062248" },
  { "title": "Kraljevina_Jugoslavija", "rev": "5146816" },
  { "title": "Vesna_Pusić", "rev": "5119891" },
  { "title": "Centrifugalna_i_centripetalna_sila", "rev": "4881597" },
  { "title": "Tlak", "rev": "5133939" },
  { "title": "Evolucija", "rev": "5107680" },
  { "title": "Krvni_tlak", "rev": "5021495" },
  { "title": "Srce_Isusovo", "rev": "5033592" },
  { "title": "Ivan_Perišić", "rev": "5112856" },
  { "title": "Brzina_zvuka", "rev": "4771635" },
  { "title": "Pristupanje_Hrvatske_Europskoj_uniji", "rev": "5053209" },
  { "title": "22._lipnja", "rev": "5094255" },
  { "title": "Instagram", "rev": "5159111" },
  { "title": "Svjetska_književnost", "rev": "3965092" },
  { "title": "Pomoćni_glagoli", "rev": "5051401" },
  { "title": "Blaženi_Alojzije_Stepinac", "rev": "5073209" },
  { "title": "Islamski_kalendar", "rev": "5135559" },
  { "title": "Marihuana", "rev": "5158242" },
  { "title": "Vukovar", "rev": "5130242" },
  { "title": "Amfiteatar_u_Puli", "rev": "5083083" },
  { "title": "Ivan_Pernar_(1985.)", "rev": "5150307" },
  { "title": "Japan", "rev": "5107247" },
  { "title": "Futur_prvi", "rev": "5087085" },
  { "title": "UDBA", "rev": "5019743" },
  { "title": "Alzheimerova_bolest", "rev": "5128190" },
  { "title": "Sveta_potvrda", "rev": "4868496" },
  { "title": "Stjepan_Radić", "rev": "5114609" },
  { "title": "Dodatak:Popis_gradova_u_Hrvatskoj", "rev": "5157633" },
  { "title": "Zemljopis_Hrvatske", "rev": "5073433" },
  { "title": "Opsesivno-kompulzivni_poremećaj", "rev": "5110701" },
  { "title": "Iliri", "rev": "5150593" },
  { "title": "Isus", "rev": "5154459" },
  { "title": "Rimska_mitologija", "rev": "5066480" },
  { "title": "Mjere_za_površinu", "rev": "4922660" },
  { "title": "Pakao_(Dante)", "rev": "5150602" },
  { "title": "Nino_Raspudić", "rev": "5146612" },
  { "title": "Snaga_struje_i_električna_energija", "rev": "5124521" },
  { "title": "Obadi", "rev": "4941926" },
  { "title": "Michael_Jackson", "rev": "5132198" },
  { "title": "Hemoglobin", "rev": "4476740" },
  { "title": "Marilyn_Monroe", "rev": "5138659" },
  { "title": "Kategorija:Mjeseci_u_godini", "rev": "5130151" },
  { "title": "Ekatarina_Velika", "rev": "5033297" },
  { "title": "Kršćanstvo", "rev": "5152669" },
  { "title": "Prirodni_broj", "rev": "4979878" },
  { "title": "Metafora", "rev": "5148066" },
  { "title": "Ukrajina", "rev": "5145419" },
  { "title": "Ante_Gotovina", "rev": "5139549" },
  { "title": "Svjetsko_prvenstvo_u_nogometu_-_Brazil_2014.", "rev": "5096120" },
  { "title": "Hrvatsko_proljeće", "rev": "5116021" },
  { "title": "Vjetar", "rev": "5144437" },
  { "title": "Agnosticizam", "rev": "4958140" },
  { "title": "Đurđevački_Pijesci", "rev": "5077626" },
  { "title": "Eufemizam", "rev": "5081997" },
  { "title": "Portugal", "rev": "5107242" },
  { "title": "Mjesečnica", "rev": "4936342" },
  { "title": "Hrvatska_kuna", "rev": "5107340" },
  { "title": "Atribut", "rev": "5156696" },
  { "title": "Colonia", "rev": "5147833" },
  { "title": "Srpanj", "rev": "4210724" },
  { "title": "Šećerna_bolest", "rev": "5047084" },
  { "title": "Filipini", "rev": "4915718" },
  { "title": "Pelješki_most", "rev": "5070479" },
  { "title": "100_najboljih_knjiga_svih_vremena", "rev": "5058979" },
  { "title": "Hrvatska_ratna_mornarica", "rev": "5138524" },
  { "title": "Kondicional_sadašnji", "rev": "5135906" },
  { "title": "Trg_Republike_Hrvatske_(Zagreb)", "rev": "5111683" },
  { "title": "Svjetsko_prvenstvo_u_nogometu", "rev": "5127585" },
  { "title": "Pokolj_u_Bleiburgu", "rev": "5146361" },
  { "title": "Protestantizam", "rev": "5091686" },
  { "title": "Kralj_Arthur", "rev": "5074431" },
  { "title": "Otvorena_pitanja_u_odnosima_Hrvatske_i_Slovenije", "rev": "4533621" },
  { "title": "Dioklecijanova_palača", "rev": "5154596" },
  { "title": "Pag", "rev": "5130446" },
  { "title": "Audi_A4", "rev": "5155842" },
  { "title": "Oružane_snage_Republike_Hrvatske", "rev": "5107307" },
  { "title": "Sunčev_sustav", "rev": "5148026" },
  { "title": "Atomsko_bombardiranje_Hirošime_i_Nagasakija", "rev": "5107424" },
  { "title": "Sodoma_i_Gomora", "rev": "5078539" },
  { "title": "Antun_Branko_Šimić", "rev": "5157099" },
  { "title": "Češka", "rev": "5156849" },
  { "title": "Kvadratna_funkcija", "rev": "4902939" },
  { "title": "Sljepić", "rev": "5075637" },
  { "title": "Bitcoin", "rev": "5116867" },
  { "title": "Metonimija", "rev": "4905069" },
  { "title": "Kategorija:Hrvatski_pjevači", "rev": "5119544" },
  { "title": "Helmut_Kohl", "rev": "4912383" },
  { "title": "Žohari", "rev": "4961242" },
  { "title": "Vjenceslav_Novak", "rev": "5097478" },
  { "title": "HNK_Rijeka", "rev": "5157239" },
  { "title": "Jelena_Karleuša", "rev": "5130076" },
  { "title": "Status_zaštite", "rev": "5138931" },
  { "title": "Rumunjska", "rev": "5152347" },
  { "title": "Kazahstan", "rev": "5021774" },
  { "title": "Mjesec", "rev": "5158805" },
  { "title": "Racionalni_broj", "rev": "5002111" },
  { "title": "Ohmov_zakon", "rev": "5158754" },
  { "title": "Kevin_Durant", "rev": "5124470" },
  { "title": "Marelica", "rev": "5123397" },
  { "title": "Tony_Cetinski", "rev": "5159145" },
  { "title": "TOMOS", "rev": "5121800" },
  { "title": "Dodatak:Popis_država_po_stanovništvu", "rev": "5150212" },
  { "title": "Glagolski_pridjev", "rev": "5015409" },
  { "title": "Concept_One", "rev": "5154431" },
  { "title": "Euharistija", "rev": "5128702" },
  { "title": "Rimsko_Carstvo", "rev": "5137718" },
  { "title": "Dodatak:Srednje_škole_i_gimnazije_u_Zagrebu", "rev": "5093483" },
  { "title": "Atmosferski_tlak", "rev": "5153280" },
  { "title": "Južnoafrička_Republika", "rev": "5107256" },
  { "title": "RMS_Titanic", "rev": "5125201" },
  { "title": "Dubioza_kolektiv", "rev": "5087271" },
  { "title": "Sterilizacija", "rev": "4789317" },
  { "title": "Kružnica", "rev": "5120469" },
  { "title": "Andrej_Plenković", "rev": "5152019" },
  { "title": "Gmail", "rev": "4801375" },
  { "title": "Međunarodni_standardni_knjižni_broj", "rev": "4688387" },
  { "title": "Knin", "rev": "5156647" },
  { "title": "Wikipedija", "rev": "5100138" },
  { "title": "Brač", "rev": "5107263" },
  { "title": "Mišo_Kovač", "rev": "5157223" },
  { "title": "Nimfomanija", "rev": "5065611" },
  { "title": "Bitka_na_Kosovu_polju", "rev": "5105642" },
  { "title": "Ronaldinho", "rev": "5064188" },
  { "title": "Podljev_krvi", "rev": "4910515" },
  { "title": "Modrulj", "rev": "4939829" },
  { "title": "Sandra_Afrika", "rev": "4892029" },
  { "title": "Geometrijski_niz", "rev": "5000677" },
  { "title": "Sylvester_Stallone", "rev": "5154370" },
  { "title": "Hladni_rat", "rev": "5076681" },
  { "title": "U_registraturi", "rev": "4905582" },
  { "title": "Franz_Kafka", "rev": "5072976" },
  { "title": "Korčula", "rev": "5119697" },
  { "title": "Sušica", "rev": "4940882" },
  { "title": "Bijelo_dugme", "rev": "5035720" },
  { "title": "Bazga", "rev": "5077379" },
  { "title": "Mjenica", "rev": "4812700" },
  { "title": "Goran_Ivanišević", "rev": "4974840" },
  { "title": "Slobodno_zidarstvo", "rev": "4945232" },
  { "title": "Bršljan", "rev": "4995292" },
  { "title": "Srce", "rev": "5081724" },
  { "title": "Prva_hrvatska_nogometna_liga", "rev": "5113813" },
  { "title": "Sabirni_logor_Jasenovac", "rev": "5152162" },
  { "title": "Šijizam", "rev": "5113651" },
  { "title": "Audi_A6", "rev": "5134897" },
  { "title": "Trešnja", "rev": "5147801" },
  { "title": "More", "rev": "5124590" },
  { "title": "Newtonovi_zakoni_gibanja", "rev": "5029319" },
  { "title": "Pluskvamperfekt", "rev": "5035168" },
  { "title": "Radimir_Čačić", "rev": "4781132" },
  { "title": "Clint_Eastwood", "rev": "5092571" },
  { "title": "Empatija", "rev": "4992781" },
  { "title": "Humanizam", "rev": "5148699" },
  { "title": "Ugljikohidrati", "rev": "5051555" },
  { "title": "Ed_Sheeran", "rev": "5131416" },
  { "title": "Ana_Rucner", "rev": "4758016" },
  { "title": "Predmenstrualni_sindrom", "rev": "4476831" },
  { "title": "Roland_Garros", "rev": "4092080" },
  { "title": "Željko_Ražnatović", "rev": "5140909" },
  { "title": "Dodatak:Popis_državnih_zastava", "rev": "5098387" },
  { "title": "Električna_struja", "rev": "5046665" },
  { "title": "Marketing", "rev": "4856867" },
  { "title": "Tetanus", "rev": "4605881" },
  { "title": "Biljke", "rev": "5156984" },
  { "title": "Slezena", "rev": "4815001" },
  { "title": "Dan_neovisnosti_(Hrvatska)", "rev": "5146488" },
  { "title": "Frekvencija", "rev": "4921566" },
  { "title": "Zvonimir_Boban", "rev": "5043994" },
  { "title": "Meksiko", "rev": "5116202" },
  { "title": "Svjetlost", "rev": "4973317" },
  { "title": "Četnici", "rev": "5115952" },
  { "title": "Wolfgang_Amadeus_Mozart", "rev": "5137603" },
  { "title": "Napoleon_Bonaparte", "rev": "5153017" },
  { "title": "Židovi", "rev": "4858282" },
  { "title": "Rad_(fizika)", "rev": "5143610" },
  { "title": "Google_Maps", "rev": "5040006" },
  { "title": "Trogir", "rev": "5155494" },
  { "title": "Novi_Sad", "rev": "5107210" },
  { "title": "Paradigma", "rev": "4961591" },
  { "title": "Trigonometrija", "rev": "4836746" },
  { "title": "MPV", "rev": "4791838" },
  { "title": "Psihologija", "rev": "4876476" },
  { "title": "Naša_mala_klinika", "rev": "5081273" },
  { "title": "Inteligencija", "rev": "5051690" },
  { "title": "John_F._Kennedy", "rev": "5125865" },
  { "title": "Gravitacija", "rev": "5107314" },
  { "title": "Europsko_prvenstvo_u_nogometu_-_Francuska_2016.", "rev": "5141785" },
  { "title": "Škorpion_(znak)", "rev": "4575737" },
  { "title": "Čile", "rev": "5107300" },
  { "title": "Cipar", "rev": "5079798" },
  { "title": "Brzina_svjetlosti", "rev": "5154108" },
  { "title": "Vijetnamski_rat", "rev": "5135540" },
  { "title": "Danska", "rev": "5103940" },
  { "title": "Popis_zemalja_po_BDP-u_(PKM)_per_capita", "rev": "4992753" },
  { "title": "Kune", "rev": "4878656" },
  { "title": "Barcelona", "rev": "5131752" },
  { "title": "Električni_otpor", "rev": "4904596" },
  { "title": "Preobrazba_(Kafka)", "rev": "4968891" },
  { "title": "Sjeverna_Amerika", "rev": "5063806" },
  { "title": "Željezo", "rev": "5157002" },
  { "title": "Elipsa", "rev": "4122999" },
  { "title": "Glagolski_prilog", "rev": "5094082" },
  { "title": "UEFA_Liga_prvaka_2016./17.", "rev": "5012055" },
  { "title": "Hrvatska_kopnena_vojska", "rev": "5138122" },
  { "title": "Bjelouška", "rev": "4909251" },
  { "title": "Bugarska", "rev": "5107254" },
  { "title": "Matični_broj_građana", "rev": "5033424" },
  { "title": "Lucifer", "rev": "5141409" },
  { "title": "Pi_(broj)", "rev": "5147460" },
  { "title": "Lepa_Brena", "rev": "4786739" },
  { "title": "Kornjače", "rev": "5089711" },
  { "title": "Islamska_država", "rev": "5096501" },
  { "title": "Moskva", "rev": "5108354" },
  { "title": "Željko_Bebek", "rev": "5131315" },
  { "title": "Olimpijske_igre", "rev": "5148305" },
  { "title": "Evolucija_čovjeka", "rev": "5010676" },
  { "title": "Srednji_vijek", "rev": "5032306" },
  { "title": "Svibanj", "rev": "4723644" },
  { "title": "Velebit", "rev": "5154393" },
  { "title": "Eminem", "rev": "5136513" },
  { "title": "Lana_Jurčević", "rev": "5123485" },
  { "title": "Vinkovci", "rev": "5159339" },
  { "title": "Hvar", "rev": "5147679" },
  { "title": "Sankt-Peterburg", "rev": "5050916" },
  { "title": "YouTube", "rev": "5144175" },
  { "title": "Vincent_van_Gogh", "rev": "5010976" },
  { "title": "Imenice", "rev": "5088038" },
  { "title": "Roman", "rev": "5074770" },
  { "title": "Johnny_Depp", "rev": "5106218" },
  { "title": "Poremećaj_hiperaktivnosti_i_deficita_pažnje", "rev": "5155655" },
  { "title": "Euro", "rev": "5079888" },
  { "title": "Zub", "rev": "5080844" },
  { "title": "Hipofiza", "rev": "4880710" },
  { "title": "Prosti_broj", "rev": "5081398" },
  { "title": "Transformator", "rev": "5043376" },
  { "title": "Sofoklo", "rev": "5097465" },
  { "title": "Ekspresionizam", "rev": "5152883" },
  { "title": "Bosna_i_Hercegovina_u_Osmanskom_Carstvu", "rev": "5087773" },
  { "title": "Oliver_Dragojević", "rev": "5154864" },
  { "title": "Testosteron", "rev": "4476818" },
  { "title": "Finska", "rev": "5054151" },
  { "title": "Rimac_Automobili", "rev": "5143825" },
  { "title": "Neda_Ukraden", "rev": "5071225" },
  { "title": "Crna_udovica", "rev": "4704499" },
  { "title": "Pjesničke_slike", "rev": "5149731" },
  { "title": "Moment_inercije", "rev": "4753455" },
  { "title": "Leptiri", "rev": "5093765" },
  { "title": "Dmitar_Zvonimir", "rev": "5148868" },
  { "title": "Presveto_Trojstvo_(svetkovina)", "rev": "4764078" },
  { "title": "Sunce", "rev": "5107088" },
  { "title": "Klasicizam", "rev": "5047862" },
  { "title": "Sovjetski_Savez", "rev": "5149834" },
  { "title": "Selena_Gomez", "rev": "5154077" },
  { "title": "Sisak", "rev": "5159611" },
  { "title": "Burj_Khalifa", "rev": "5052764" },
  { "title": "Sergio_Ramos", "rev": "5125940" },
  { "title": "Vampirski_dnevnici", "rev": "5129941" },
  { "title": "Vlasta_Pavić", "rev": "4883178" },
  { "title": "Dalmacija", "rev": "5150751" },
  { "title": "Komunikacija", "rev": "4939869" },
  { "title": "Karolina", "rev": "4700717" },
  { "title": "Bitka_na_Sutjesci", "rev": "5112113" },
  { "title": "Tomislavgrad", "rev": "5156800" },
  { "title": "Singapur", "rev": "5130794" },
  { "title": "Venecija", "rev": "5156341" },
  { "title": "Životinje", "rev": "5153176" },
  { "title": "Azbest", "rev": "5025097" },
  { "title": "Masne_kiseline", "rev": "5155999" },
  { "title": "Kralj_Tomislav", "rev": "5151321" },
  { "title": "Bahrein", "rev": "5159820" },
  { "title": "Zvuk", "rev": "4886475" },
  { "title": "Gruzija", "rev": "5140894" },
  { "title": "August_Šenoa", "rev": "5153435" },
  { "title": "Vitiligo", "rev": "4869203" },
  { "title": "Poreč", "rev": "5150514" },
  { "title": "Genocid_u_Srebrenici", "rev": "5141478" },
  { "title": "Antarktika", "rev": "4995730" },
  { "title": "Kategorija:Jadranske_ribe", "rev": "4290337" },
  { "title": "Republika_Srpska", "rev": "5120961" },
  { "title": "Operacija_Barbarossa", "rev": "4952266" },
  { "title": "Nin", "rev": "5155839" },
  { "title": "Kukci", "rev": "4984240" },
  { "title": "Ante_Starčević", "rev": "5084674" },
  { "title": "Bjelica", "rev": "4910986" },
  { "title": "Popis_valuta_po_državama", "rev": "4848195" },
  { "title": "Epilepsija", "rev": "5121875" },
  { "title": "Popis_mitoloških_bića", "rev": "5137455" },
  { "title": "Leonardo_da_Vinci", "rev": "5156384" },
  { "title": "Toplinski_kapacitet", "rev": "4965950" },
  { "title": "Ljubav_u_zaleđu", "rev": "5142403" },
  { "title": "Sila", "rev": "4708021" },
  { "title": "Neymar", "rev": "5151500" },
  { "title": "Bjelovar", "rev": "5151316" },
  { "title": "Ivanjski_krijesovi", "rev": "5098088" },
  { "title": "Livno", "rev": "5158187" },
  { "title": "Moldavija", "rev": "5141359" },
  { "title": "Argentina", "rev": "5107260" },
  { "title": "Jajce", "rev": "5157590" },
  { "title": "Albert_Camus", "rev": "5139992" },
  { "title": "Krijesnice", "rev": "5134429" },
  { "title": "Jednačenje_po_zvučnosti", "rev": "4967379" },
  { "title": "Temperatura", "rev": "4907447" },
  { "title": "Brodovlje_Hrvatske_ratne_mornarice", "rev": "4775619" },
  { "title": "Bruto_domaći_proizvod", "rev": "4736844" },
  { "title": "Golden_State_Warriors", "rev": "5095422" },
  { "title": "Engleska", "rev": "5097165" },
  { "title": "Veznici", "rev": "5138328" },
  { "title": "Crohnova_bolest", "rev": "4662427" },
  { "title": "Bura", "rev": "5105319" },
  { "title": "Dražen_Bošnjaković", "rev": "5152431" },
  { "title": "Mercedes-Benz_C-klasa", "rev": "4831390" },
  { "title": "Makarska", "rev": "5151333" },
  { "title": "Zauvijek_susjedi", "rev": "5130523" },
  { "title": "Stephen_Hawking", "rev": "5081579" },
  { "title": "Božanstvena_komedija", "rev": "5014890" },
  { "title": "Bitange_i_princeze", "rev": "5140945" },
  { "title": "Kilogram", "rev": "4655831" },
  { "title": "Giht", "rev": "5057710" },
  { "title": "Stih", "rev": "5090670" },
  { "title": "Religija", "rev": "4970816" },
  { "title": "Egipat", "rev": "5107258" },
  { "title": "Grčki_alfabet", "rev": "5030954" },
  { "title": "Lajmska_borelioza", "rev": "4730546" },
  { "title": "Kamilica", "rev": "5136619" },
  { "title": "Banja_Luka", "rev": "5157548" },
  { "title": "Rade_Šerbedžija", "rev": "5091450" },
  { "title": "Zagrebačka_katedrala", "rev": "5130681" },
  { "title": "Bernoullijeva_jednadžba", "rev": "4970806" },
  { "title": "Ljubljana", "rev": "5144785" },
  { "title": "Atletika", "rev": "5135673" },
  { "title": "Tratinčica", "rev": "5147478" },
  { "title": "Divlje_jagode", "rev": "5136104" },
  { "title": "Che_Guevara", "rev": "5101021" },
  { "title": "Demencija", "rev": "4917476" },
  { "title": "Snošaj", "rev": "4853326" },
  { "title": "Dodatak:Popis_registracijskih_oznaka_za_cestovna_vozila_u_Njemačkoj", "rev": "5124617" },
  { "title": "Francuska_revolucija", "rev": "5157048" },
  { "title": "Slavenska_mitologija", "rev": "5145360" },
  { "title": "Stipe_Pletikosa", "rev": "5153154" },
  { "title": "Sava", "rev": "5135798" },
  { "title": "Munja", "rev": "5094713" },
  { "title": "Tuzla", "rev": "5159810" },
  { "title": "Mile_Kitić", "rev": "5133454" },
  { "title": "Paracetamol", "rev": "4743346" },
  { "title": "Zračna_luka_„Franjo_Tuđman”", "rev": "5151011" },
  { "title": "Slaveni", "rev": "5138288" },
  { "title": "Čagljevi", "rev": "5137791" },
  { "title": "Vektor", "rev": "5031738" },
  { "title": "Ruđer_Bošković", "rev": "5149208" },
  { "title": "Obična_čančara", "rev": "5001162" },
  { "title": "Pleonazam", "rev": "5063600" },
  { "title": "Trputac", "rev": "5123214" },
  { "title": "Slovačka", "rev": "5060363" },
  { "title": "Muhamed", "rev": "5122956" },
  { "title": "Kocka", "rev": "5044038" },
  { "title": "Sjeverna_Koreja", "rev": "5155380" },
  { "title": "Nikola_Pokrivač", "rev": "4956111" },
  { "title": "Nautička_milja", "rev": "4066877" },
  { "title": "Amonijak", "rev": "5057336" },
  { "title": "Jennifer_Lopez", "rev": "5139436" },
  { "title": "Bakterije", "rev": "5148419" },
  { "title": "Njutn", "rev": "4803350" },
  { "title": "Štitna_žlijezda", "rev": "4953259" },
  { "title": "Logaritam", "rev": "5015811" },
  { "title": "Ose", "rev": "5133838" },
  { "title": "Piramida_(geometrija)", "rev": "4974387" },
  { "title": "André_Rieu", "rev": "4594219" },
  { "title": "Nogometno_igralište", "rev": "4052568" },
  { "title": "Zlatan_Stipišić_-_Gibonni", "rev": "5119390" },
  { "title": "Goran_Bare", "rev": "5158705" },
  { "title": "Hrvatski_narodni_preporod", "rev": "5015390" },
  { "title": "Popis_kostiju_kostura_čovjeka", "rev": "4778668" },
  { "title": "Keanu_Reeves", "rev": "5064142" },
  { "title": "Magazin_(sastav)", "rev": "5082234" },
  { "title": "Brzina", "rev": "4879209" },
  { "title": "Sekularizam", "rev": "4924577" },
  { "title": "Kaštela", "rev": "5141101" },
  { "title": "Marija_(majka_Isusova)", "rev": "5045117" },
  { "title": "Napon", "rev": "4994104" },
  { "title": "Film", "rev": "5074775" },
  { "title": "Pneumonija", "rev": "4940030" },
  { "title": "Wikipedija:Opće_odricanje_od_odgovornosti", "rev": "2257293" },
  { "title": "Vis", "rev": "5137226" },
  { "title": "Luka_Cindrić", "rev": "5118669" },
  { "title": "Čovjek", "rev": "5140625" },
  { "title": "Tranzistor", "rev": "4970812" },
  { "title": "Nargila", "rev": "5142953" },
  { "title": "Mazohizam", "rev": "4932510" },
  { "title": "Hemoroidi", "rev": "4892828" },
  { "title": "Klitoris", "rev": "5086211" },
  { "title": "Sonja_i_bik_(2012.)", "rev": "4890451" },
  { "title": "BMW_serije_5", "rev": "4818219" },
  { "title": "Kvadar", "rev": "5059029" },
  { "title": "Deoksiribonukleinska_kiselina", "rev": "5105201" },
  { "title": "Električno_polje", "rev": "5055872" },
  { "title": "Korelacija", "rev": "5006641" },
  { "title": "Muhammad_Ali", "rev": "5015311" },
  { "title": "Kantarion", "rev": "5157836" },
  { "title": "Paskal", "rev": "5052088" },
  { "title": "Ujedinjeni_narodi", "rev": "5145215" },
  { "title": "Stožac", "rev": "4672714" },
  { "title": "Republika_Srpska_Krajina", "rev": "5149898" },
  { "title": "Radioaktivnost", "rev": "5107423" },
  { "title": "Konjska_snaga", "rev": "4997653" },
  { "title": "Bitka_na_Neretvi", "rev": "5002550" },
  { "title": "Heroin", "rev": "5115976" },
  { "title": "Gradacija_(figura)", "rev": "4960330" },
  { "title": "Zakon_braće", "rev": "5062408" },
  { "title": "Saša_Broz", "rev": "5108379" },
  { "title": "Feminizam", "rev": "5136494" },
  { "title": "Hrvatska_Republika_Herceg-Bosna", "rev": "5147902" },
  { "title": "Magnetsko_polje", "rev": "5094349" },
  { "title": "Debitna_kartica", "rev": "4623275" },
  { "title": "Imotski", "rev": "5147501" },
  { "title": "Blaženka_Divjak", "rev": "4935911" },
  { "title": "Ogulin", "rev": "5142915" },
  { "title": "Atom", "rev": "5107315" },
  { "title": "Antiteza", "rev": "3930215" },
  { "title": "Cres", "rev": "5107264" },
  { "title": "Ena_Begović", "rev": "5088967" },
  { "title": "Bitka_kod_Siska", "rev": "5149405" },
  { "title": "Opeklina", "rev": "5026259" },
  { "title": "Faust_Vrančić", "rev": "5114607" },
  { "title": "Motor_s_unutarnjim_izgaranjem", "rev": "5014001" },
  { "title": "Jagoda", "rev": "5151076" },
  { "title": "Hinduizam", "rev": "5155966" },
  { "title": "Antifašizam", "rev": "5127218" },
  { "title": "Emil_Vlajki", "rev": "4855471" },
  { "title": "Jasmin_Stavros", "rev": "4990928" },
  { "title": "Lujzijana", "rev": "5099081" },
  { "title": "Sibilarizacija", "rev": "4986894" },
  { "title": "Toše_Proeski", "rev": "5145759" },
  { "title": "Dino_Dvornik", "rev": "5130869" },
  { "title": "Njemačke_savezne_pokrajine", "rev": "4455402" },
  { "title": "Električni_naboj", "rev": "5147961" },
  { "title": "Pridjevi", "rev": "5076266" },
  { "title": "Proširenje_Europske_unije", "rev": "5107928" },
  { "title": "Vjekoslav_Luburić", "rev": "5157499" },
  { "title": "Avion", "rev": "5033040" },
  { "title": "Etanol", "rev": "4950261" },
  { "title": "Impresionizam", "rev": "4932322" },
  { "title": "Elektroliza", "rev": "5143392" },
  { "title": "Aliteracija", "rev": "5150804" },
  { "title": "Oksidacija", "rev": "5121790" },
  { "title": "Budizam", "rev": "5153457" },
  { "title": "Nacionalni_park_Krka", "rev": "5093717" },
  { "title": "Leukemija", "rev": "5090724" },
  { "title": "Smokva", "rev": "5156691" },
  { "title": "Infekcija_mokraćnog_sustava", "rev": "4029030" },
  { "title": "S.A.R.S.", "rev": "5057050" },
  { "title": "Litva", "rev": "5088370" },
  { "title": "Iracionalni_broj", "rev": "4972720" },
  { "title": "Bakar_(element)", "rev": "5107698" },
  { "title": "Gospić", "rev": "5130457" },
  { "title": "Prag", "rev": "5157489" },
  { "title": "Cardiff_(Wales)", "rev": "3997798" },
  { "title": "Sifilis", "rev": "5032649" },
  { "title": "Banovina_Hrvatska", "rev": "5125536" },
  { "title": "Slavonija", "rev": "5148961" },
  { "title": "Pčele", "rev": "5092553" },
  { "title": "Predikat", "rev": "4975515" },
  { "title": "Ernest_Hemingway", "rev": "5058319" },
  { "title": "Hrast", "rev": "5094129" },
  { "title": "Višnja", "rev": "4934323" },
  { "title": "Downov_sindrom", "rev": "4960942" },
  { "title": "RDW", "rev": "4475764" },
  { "title": "Koeficijent_smjera_pravca", "rev": "4712546" },
  { "title": "Kineski_zid", "rev": "5040505" },
  { "title": "Strijelac_(znak)", "rev": "4460171" },
  { "title": "Jozefina", "rev": "5156739" },
  { "title": "Entropija", "rev": "4866069" },
  { "title": "Dundo_Maroje", "rev": "5118786" },
  { "title": "Ronaldo_Luís_Nazário_de_Lima", "rev": "4994259" },
  { "title": "Indijanci", "rev": "5069632" },
  { "title": "Seljačka_buna", "rev": "5151729" },
  { "title": "Energija", "rev": "5154804" },
  { "title": "Mravi", "rev": "5053868" },
  { "title": "Janjevci", "rev": "5159481" },
  { "title": "Avari", "rev": "5046473" },
  { "title": "Stephen_Curry", "rev": "5085945" },
  { "title": "Gaj_Julije_Cezar", "rev": "5159500" },
  { "title": "Stanovništvo_Hrvatske", "rev": "5141111" },
  { "title": "Operacija_Bljesak", "rev": "5073298" },
  { "title": "Geronimo", "rev": "4329339" },
  { "title": "C-reaktivni_protein", "rev": "5126455" },
  { "title": "Periodni_sustav_elemenata", "rev": "5121137" },
  { "title": "Josipa_Lisac", "rev": "5155567" },
  { "title": "Avangarda", "rev": "4950742" },
  { "title": "Vrana", "rev": "5052094" },
  { "title": "Jugoslavenska_narodna_armija", "rev": "5134906" },
  { "title": "Križarski_ratovi", "rev": "5150482" },
  { "title": "Donna_Vekić", "rev": "5124042" },
  { "title": "Futur_drugi", "rev": "4951858" },
  { "title": "Termodinamika", "rev": "4862297" },
  { "title": "Vremenska_zona", "rev": "5110274" },
  { "title": "Ku_Klux_Klan", "rev": "5153848" },
  { "title": "Aluminij", "rev": "4919621" },
  { "title": "Zlato", "rev": "5107675" },
  { "title": "Cijevni_navoj", "rev": "4013381" },
  { "title": "Hepatitis_C", "rev": "5143807" },
  { "title": "Biograd_na_Moru", "rev": "5123076" },
  { "title": "Kategorija:Hrvatske_serije", "rev": "4961732" },
  { "title": "Parafilija", "rev": "4666317" },
  { "title": "Maroko", "rev": "5111730" },
  { "title": "Psilocibinske_gljive", "rev": "5065336" },
  { "title": "Aritmetički_niz", "rev": "4598299" },
  { "title": "Bihać", "rev": "5153516" },
  { "title": "Vladimir_Nazor", "rev": "5152186" },
  { "title": "Telekom_arena", "rev": "4970785" },
  { "title": "Kolovoz", "rev": "4486147" },
  { "title": "Prljavo_kazalište", "rev": "5159092" },
  { "title": "Henrik_Ibsen", "rev": "4886178" },
  { "title": "Beta_blokatori", "rev": "5011964" },
  { "title": "Fjodor_Emelianenko", "rev": "5147369" },
  { "title": "Nihilizam", "rev": "5134852" },
  { "title": "Toplina", "rev": "4856418" },
  { "title": "Wikipedija:Upload", "rev": "3242818" },
  { "title": "Objekt", "rev": "4905450" },
  { "title": "Filozofija", "rev": "5097156" },
  { "title": "Zaštita_okoliša", "rev": "5057622" },
  { "title": "Budimpešta", "rev": "5111439" },
  { "title": "Tin_Ujević", "rev": "5049609" },
  { "title": "Elektronička_pošta", "rev": "5001383" },
  { "title": "Altruizam", "rev": "4993056" },
  { "title": "Indira_Levak", "rev": "5149595" },
  { "title": "Goli_otok", "rev": "4912148" },
  { "title": "Uzgon", "rev": "4785536" },
  { "title": "Ivan_Pavao_II.", "rev": "5073131" },
  { "title": "Kim_Kardashian", "rev": "5129387" },
  { "title": "Ivan_Čehok", "rev": "5111872" },
  { "title": "John_Lennon", "rev": "5151717" },
  { "title": "Monako", "rev": "4861360" },
  { "title": "Hrvatska_demokratska_zajednica", "rev": "5141523" },
  { "title": "Armenija", "rev": "5064283" },
  { "title": "Arsen_Dedić", "rev": "5151869" },
  { "title": "Kondicional_prošli", "rev": "5101587" },
  { "title": "Romi", "rev": "5078436" },
  { "title": "Ivana_Brlić-Mažuranić", "rev": "5150168" },
  { "title": "Karma", "rev": "5096062" },
  { "title": "Pakistan", "rev": "4935015" },
  { "title": "Kisik", "rev": "5150864" },
  { "title": "Trst", "rev": "5117488" },
  { "title": "Mafija", "rev": "5027432" },
  { "title": "Mali_Lošinj", "rev": "5159805" },
  { "title": "Velika_Gorica", "rev": "5151140" },
  { "title": "Bosanskohercegovačka_nogometna_reprezentacija", "rev": "5152066" },
  { "title": "Pelješac", "rev": "5074286" },
  { "title": "Firenca", "rev": "4903360" },
  { "title": "Tiger_Woods", "rev": "5149920" },
  { "title": "Domaća_kokoš", "rev": "5078084" },
  { "title": "Tko_pjeva_zlo_ne_misli", "rev": "5130604" },
  { "title": "Aleksandar_Veliki", "rev": "5156468" },
  { "title": "Ivan_Mažuranić", "rev": "5099603" },
  { "title": "Kravica_(slap)", "rev": "4958245" },
  { "title": "Željka_Markić", "rev": "5145375" },
  { "title": "Pivo", "rev": "5130406" },
  { "title": "Trenje", "rev": "4679862" },
  { "title": "Kiseline", "rev": "5148995" },
  { "title": "Leukociti", "rev": "4758038" },
  { "title": "Komarci", "rev": "5141641" },
  { "title": "PH", "rev": "4896820" },
  { "title": "Lav", "rev": "4941390" },
  { "title": "Parni_valjak", "rev": "5001953" },
  { "title": "JAS_39_Gripen", "rev": "5064224" },
  { "title": "Rujan", "rev": "4360929" },
  { "title": "Teorija_relativnosti", "rev": "4877881" },
  { "title": "Promjer", "rev": "4971890" },
  { "title": "Rab", "rev": "4584845" },
  { "title": "Deveti_saziv_Hrvatskog_sabora", "rev": "5156299" },
  { "title": "Bizant", "rev": "4844507" },
  { "title": "Stari_zavjet", "rev": "4952797" },
  { "title": "Sumamed", "rev": "4850448" },
  { "title": "Osobni_identifikacijski_broj", "rev": "4907640" },
  { "title": "Charles_Darwin", "rev": "5136426" },
  { "title": "Opatija", "rev": "5119730" },
  { "title": "Dodatak:Popis_svjetskih_dana", "rev": "5031921" },
  { "title": "Grička_vještica", "rev": "5033240" },
  { "title": "Korozija", "rev": "5021081" },
  { "title": "Indonezija", "rev": "5052453" },
  { "title": "Berlinski_zid", "rev": "5113242" },
  { "title": "Hiperbola_(figura)", "rev": "4265832" },
  { "title": "Latvija", "rev": "4906860" },
  { "title": "Bubamare", "rev": "5110667" },
  { "title": "Socijalizam", "rev": "5107410" },
  { "title": "Hamburg", "rev": "5156603" },
  { "title": "Ružmarin", "rev": "5147972" },
  { "title": "Sinonim", "rev": "4074976" },
  { "title": "Nadbubrežna_žlijezda", "rev": "3945245" },
  { "title": "Gavrilo_Princip", "rev": "5072251" },
  { "title": "RK_Vardar_Skoplje", "rev": "5069345" },
  { "title": "Djevica_(znak)", "rev": "5124466" },
  { "title": "Marko_Marulić", "rev": "5108242" },
  { "title": "Istarska_županija", "rev": "5120282" },
  { "title": "Porez_na_dodanu_vrijednost", "rev": "5072722" },
  { "title": "Dodatak:Popis_epizoda_serije_Lud,_zbunjen,_normalan", "rev": "5135551" },
  { "title": "Sivi_vuk", "rev": "5130161" },
  { "title": "A.C._Milan", "rev": "5043888" },
  { "title": "Rak_pluća", "rev": "4940057" },
  { "title": "Kvalifikacije_za_Svjetsko_prvenstvo_u_nogometu_2018._(UEFA)", "rev": "5030071" },
  { "title": "Hrvatski_vladari", "rev": "5157949" },
  { "title": "Vlada_Republike_Hrvatske", "rev": "5135449" },
  { "title": "Čempres", "rev": "5092862" },
  { "title": "Požega", "rev": "5150134" },
  { "title": "Mirko_Filipović", "rev": "5144002" },
  { "title": "Boks", "rev": "5051321" },
  { "title": "Kartezijev_koordinatni_sustav", "rev": "5157655" },
  { "title": "Dwayne_Johnson", "rev": "5118041" },
  { "title": "Zavarivanje_TIG_postupkom", "rev": "4184811" },
  { "title": "Mljet", "rev": "5080903" },
  { "title": "Abdest", "rev": "5084270" },
  { "title": "BMW", "rev": "5132507" },
  { "title": "Južna_Amerika", "rev": "5081008" },
  { "title": "Imperativ", "rev": "5076727" },
  { "title": "Dodatak:Popis_država_po_površini", "rev": "4986650" },
  { "title": "Selam", "rev": "4621667" },
  { "title": "Alkoholizam", "rev": "5056472" },
  { "title": "Gospa_Fatimska", "rev": "4903502" },
  { "title": "Glukoza", "rev": "5009388" },
  { "title": "Jadrolinija", "rev": "5159696" },
  { "title": "Vlasi", "rev": "5046177" },
  { "title": "Mjanmar", "rev": "5126541" },
  { "title": "Humani_papiloma_virus", "rev": "4927884" },
  { "title": "Popis_BMW-ovih_motora", "rev": "5064179" }
]}
